hippocrates/__init__.py
hippocrates/command_line.py
hippocrates/results.py
hippocrates/data/__init__.py
hippocrates/data/fetcher.py
hippocrates/graphing/__init__.py
hippocrates/graphing/generator.py
hippocrates/questionnaires/__init__.py
hippocrates/questionnaires/base.py
hippocrates/questionnaires/models.py
hippocrates/questionnaires/beck_depression_index/__init__.py
hippocrates/questionnaires/beck_depression_index/assessment.py
hippocrates/questionnaires/beck_depression_index/question_set.json
hippocrates/questionnaires/gad2/__init__.py
hippocrates/questionnaires/gad2/assessment.py
hippocrates/questionnaires/gad2/question_set.json
hippocrates/questionnaires/gad7/__init__.py
hippocrates/questionnaires/gad7/assessment.py
hippocrates/questionnaires/gad7/question_set.json
hippocrates/questionnaires/mood_tracker/__init__.py
hippocrates/questionnaires/mood_tracker/assessment.py
hippocrates/questionnaires/mood_tracker/question_set.json
hippocrates/questionnaires/phq2/__init__.py
hippocrates/questionnaires/phq2/assessment.py
hippocrates/questionnaires/phq2/question_set.json
hippocrates/questionnaires/phq9/__init__.py
hippocrates/questionnaires/phq9/assessment.py
hippocrates/questionnaires/phq9/question_set.json
hippocrates/questionnaires/rosenberg_self_esteem/__init__.py
hippocrates/questionnaires/rosenberg_self_esteem/assessment.py
hippocrates/questionnaires/rosenberg_self_esteem/question_set.json
hippocrates/utils/__init__.py
hippocrates/utils/generate_results.py
tests/data/__init__.py
tests/data/test_fetcher.py
tests/questionnaires/__init__.py
tests/questionnaires/test_base.py
tests/questionnaires/test_models.py
tests/questionnaires/beck_depression_index/__init__.py
tests/questionnaires/beck_depression_index/test_beck_depression_index_assessment.py
tests/questionnaires/gad2/__init__.py
tests/questionnaires/gad2/test_gad2_assessment.py
tests/questionnaires/gad7/__init__.py
tests/questionnaires/gad7/test_gad7_assessment.py
tests/questionnaires/phq2/__init__.py
hippocrates-0.4.0.dist-info/LICENSE
hippocrates-0.4.0.dist-info/METADATA
hippocrates-0.4.0.dist-info/WHEEL
hippocrates-0.4.0.dist-info/entry_points.txt
hippocrates-0.4.0.dist-info/top_level.txt
hippocrates-0.4.0.dist-info/RECORD
