Metadata-Version: 2.1
Name: hippocrates
Version: 0.4.0
Summary: Mental health questionnaires.
Home-page: https://github.com/chrishannam/hippocrates
Author: Chris Hannam
Author-email: ch@chrishannam.co.uk
License: UNKNOWN
Platform: UNKNOWN
Classifier: Programming Language :: Python :: 3
Classifier: License :: OSI Approved :: Apache Software License
Classifier: Operating System :: OS Independent
Requires-Dist: click (==7.0)
Requires-Dist: pick (>=0.6.4)
Requires-Dist: tabulate (>=0.8.2)
